<?xml version="1.0"?>
<opencv_storage>
<stage0>
  <maxWeakCount>2</maxWeakCount>
  <stageThreshold>-2.7096900343894958e-01</stageThreshold>
  <weakClassifiers>
    <_>
      <internalNodes>
        0 -1 99116 4.8958463594317436e-04</internalNodes>
      <leafValues>
        -9.8518520593643188e-01 6.1860466003417969e-01</leafValues></_>
    <_>
      <internalNodes>
        0 -1 5166 4.6770982444286346e-03</internalNodes>
      <leafValues>
        -6.9436025619506836e-01 7.1421617269515991e-01</leafValues></_></weakClassifiers></stage0>
</opencv_storage>
