<?xml version="1.0"?>
<opencv_storage>
<stage1>
  <maxWeakCount>3</maxWeakCount>
  <stageThreshold>-9.8840868473052979e-01</stageThreshold>
  <weakClassifiers>
    <_>
      <internalNodes>
        0 -1 896 0 67108864 0 83951616 -2004745720 -813260256
        -2013263862 -1357961201</internalNodes>
      <leafValues>
        -9.4074076414108276e-01 8.5263156890869141e-01</leafValues></_>
    <_>
      <internalNodes>
        0 -1 3826 0 0 0 285278209 75497472 1195377152 33027 -16004565</internalNodes>
      <leafValues>
        -8.7604385614395142e-01 9.3397080898284912e-01</leafValues></_>
    <_>
      <internalNodes>
        0 -1 244 132 -1652227928 16777232 268697728 -1731688018
        -1165047317 -1945596532 -1079473775</internalNodes>
      <leafValues>
        -9.3559199571609497e-01 8.2837587594985962e-01</leafValues></_></weakClassifiers></stage1>
</opencv_storage>
