<?xml version="1.0"?>
<opencv_storage>
<stage1>
  <maxWeakCount>3</maxWeakCount>
  <stageThreshold>-6.3723802566528320e-01</stageThreshold>
  <weakClassifiers>
    <_>
      <internalNodes>
        0 -1 28340 5.3887933492660522e-02</internalNodes>
      <leafValues>
        -6.2736535072326660e-01 6.0448807477951050e-01</leafValues></_>
    <_>
      <internalNodes>
        0 -1 98858 -3.1212664907798171e-04</internalNodes>
      <leafValues>
        4.3752992153167725e-01 -7.7596390247344971e-01</leafValues></_>
    <_>
      <internalNodes>
        0 -1 8367 -1.8839664990082383e-03</internalNodes>
      <leafValues>
        8.8358777761459351e-01 -4.4740262627601624e-01</leafValues></_></weakClassifiers></stage1>
</opencv_storage>
